liteai_sdk/__init__.py
liteai_sdk/debug.py
liteai_sdk/logger.py
liteai_sdk/param_parser.py
liteai_sdk/stream.py
liteai_sdk/tool/__init__.py
liteai_sdk/tool/execute.py
liteai_sdk/tool/utils.py
liteai_sdk/types/__init__.py
liteai_sdk/types/exceptions.py
liteai_sdk/types/message.py
liteai_sdk-0.3.24.dist-info/licenses/LICENSE
liteai_sdk-0.3.24.dist-info/WHEEL
liteai_sdk-0.3.24.dist-info/METADATA
liteai_sdk-0.3.24.dist-info/RECORD
