Metadata-Version: 2.4
Name: liteai_sdk
Version: 0.3.24
Summary: A wrapper of LiteLLM
Author-email: BHznJNs <bhznjns@outlook.com>
Requires-Python: >=3.10
Classifier: Development Status :: 3 - Alpha
Classifier: Intended Audience :: Developers
Classifier: License :: OSI Approved :: MIT License
Classifier: Programming Language :: Python :: 3 :: Only
Classifier: Programming Language :: Python :: 3.10
Classifier: Programming Language :: Python :: 3.11
Classifier: Programming Language :: Python :: 3.12
License-File: LICENSE
Requires-Dist: litellm>=1.80.0
Requires-Dist: pydantic>=2.0.0
Requires-Dist: python-dotenv>=1.2.1 ; extra == "dev"
Requires-Dist: pytest-cov ; extra == "test"
Requires-Dist: pytest-mock ; extra == "test"
Requires-Dist: pytest-runner ; extra == "test"
Requires-Dist: pytest ; extra == "test"
Requires-Dist: pytest-github-actions-annotate-failures ; extra == "test"
Project-URL: Source, https://github.com/BHznJNs/liteai
Project-URL: Tracker, https://github.com/BHznJNs/liteai/issues
Provides-Extra: dev
Provides-Extra: test
